Workbook
Name DiscountRate: 'Assumptions'!$B$5
Name TaxRate: 'Assumptions'!$B$6
Name TerminalGrowthRate: 'Assumptions'!$B$7
Name EBITDAMargin: 'Assumptions'!$B$8
Name CapexPct: 'Assumptions'!$B$9
Name DandAPct: 'Assumptions'!$B$10
Name ARPUBase: 'Assumptions'!$B$23
Name ChurnRate: 'Assumptions'!$B$24
Name StartCustomers: 'Assumptions'!$B$25
Name CAC: 'Assumptions'!$B$26
Name GrowthRates: 'Assumptions'!$C$14:$C$18

Sheet Assumptions
A1: SaaS Financial Model — Key Assumptions
A3: Valuation Parameters
A4: Parameter | B4: Value | C4: Named Range
A5: Discount Rate (WACC) | B5: 0.1 | C5: DiscountRate
A6: Tax Rate | B6: 0.25 | C6: TaxRate
A7: Terminal Growth Rate | B7: 0.03 | C7: TerminalGrowthRate
A8: EBITDA Margin | B8: 0.3 | C8: EBITDAMargin
A9: Capex % of Revenue | B9: 0.05 | C9: CapexPct
A10: D&A % of Revenue | B10: 0.04 | C10: DandAPct
A12: Annual Revenue Growth Rates
A13: Year | B13: Label | C13: Growth Rate
A14: 1 | B14: Year 1 — 2025 | C14: 0.4
A15: 2 | B15: Year 2 — 2026 | C15: 0.35
A16: 3 | B16: Year 3 — 2027 | C16: 0.28
A17: 4 | B17: Year 4 — 2028 | C17: 0.2
A18: 5 | B18: Year 5 — 2029 | C18: 0.15
A19: ↑ Named range 'GrowthRates' = C14:C18
A21: SaaS Operating Metrics
A22: Metric | B22: Value | C22: Named Range
A23: Base ARPU (Annual, $) | B23: 12000 | C23: ARPUBase
A24: Monthly Churn Rate | B24: 0.02 | C24: ChurnRate
A25: Starting Customer Count | B25: 50 | C25: StartCustomers
A26: Customer Acquisition Cost ($) | B26: 8000 | C26: CAC

Sheet Products
A1: Product Catalog
A2: Excel Table: 'Products' | Structured-ref demo: =1-[@COGSPct]
A3: ProductID | B3: ProductName | C3: Category | D3: AnnualPrice | E3: COGSPct | F3: GrossMargin
A4: P001 | B4: Starter | C4: SMB | D4: 6000 | E4: 0.15 | F4: =1-[@COGSPct]
A5: P002 | B5: Professional | C5: Mid-Market | D5: 18000 | E5: 0.12 | F5: =1-[@COGSPct]
A6: P003 | B6: Enterprise | C6: Enterprise | D6: 60000 | E6: 0.08 | F6: =1-[@COGSPct]
A7: P004 | B7: Analytics Add-on | C7: Add-on | D7: 4800 | E7: 0.2 | F7: =1-[@COGSPct]
A8: P005 | B8: API Access | C8: Add-on | D8: 3600 | E8: 0.22 | F8: =1-[@COGSPct]

Sheet Customers
A1: Customer Database
A2: Excel Table: 'Customers' | XLOOKUP + structured refs in every formula row
A3: CustomerID | B3: CustomerName | C3: Segment | D3: ProductID | E3: ARR | F3: Status | G3: AnnualCOGS | H3: GrossProfit
A4: C001 | B4: Acme Corp | C4: Mid-Market | D4: P002 | E4: =XLOOKUP([@ProductID],Products[ProductID],Products[AnnualPrice]) | F4: Active | G4: =[@ARR]*XLOOKUP([@ProductID],Products[ProductID],Products[COGSPct]) | H4: =[@ARR]-[@AnnualCOGS]
A5: C002 | B5: TechStart Inc | C5: SMB | D5: P001 | E5: =XLOOKUP([@ProductID],Products[ProductID],Products[AnnualPrice]) | F5: Active | G5: =[@ARR]*XLOOKUP([@ProductID],Products[ProductID],Products[COGSPct]) | H5: =[@ARR]-[@AnnualCOGS]
A6: C003 | B6: GlobalNet | C6: Enterprise | D6: P003 | E6: =XLOOKUP([@ProductID],Products[ProductID],Products[AnnualPrice]) | F6: Active | G6: =[@ARR]*XLOOKUP([@ProductID],Products[ProductID],Products[COGSPct]) | H6: =[@ARR]-[@AnnualCOGS]
A7: C004 | B7: Pixel Labs | C7: SMB | D7: P001 | E7: =XLOOKUP([@ProductID],Products[ProductID],Products[AnnualPrice]) | F7: Churned | G7: =[@ARR]*XLOOKUP([@ProductID],Products[ProductID],Products[COGSPct]) | H7: =[@ARR]-[@AnnualCOGS]
A8: C005 | B8: DataDriven Co | C8: Mid-Market | D8: P002 | E8: =XLOOKUP([@ProductID],Products[ProductID],Products[AnnualPrice]) | F8: Active | G8: =[@ARR]*XLOOKUP([@ProductID],Products[ProductID],Products[COGSPct]) | H8: =[@ARR]-[@AnnualCOGS]
A9: C006 | B9: SkyBridge Ltd | C9: Enterprise | D9: P003 | E9: =XLOOKUP([@ProductID],Products[ProductID],Products[AnnualPrice]) | F9: Active | G9: =[@ARR]*XLOOKUP([@ProductID],Products[ProductID],Products[COGSPct]) | H9: =[@ARR]-[@AnnualCOGS]
A10: C007 | B10: Neon Startup | C10: SMB | D10: P004 | E10: =XLOOKUP([@ProductID],Products[ProductID],Products[AnnualPrice]) | F10: Active | G10: =[@ARR]*XLOOKUP([@ProductID],Products[ProductID],Products[COGSPct]) | H10: =[@ARR]-[@AnnualCOGS]
A11: C008 | B11: CloudVault | C11: Mid-Market | D11: P002 | E11: =XLOOKUP([@ProductID],Products[ProductID],Products[AnnualPrice]) | F11: Active | G11: =[@ARR]*XLOOKUP([@ProductID],Products[ProductID],Products[COGSPct]) | H11: =[@ARR]-[@AnnualCOGS]
A12: C009 | B12: IronForge LLC | C12: Enterprise | D12: P003 | E12: =XLOOKUP([@ProductID],Products[ProductID],Products[AnnualPrice]) | F12: Active | G12: =[@ARR]*XLOOKUP([@ProductID],Products[ProductID],Products[COGSPct]) | H12: =[@ARR]-[@AnnualCOGS]
A13: C010 | B13: Quickfire Inc | C13: SMB | D13: P001 | E13: =XLOOKUP([@ProductID],Products[ProductID],Products[AnnualPrice]) | F13: Churned | G13: =[@ARR]*XLOOKUP([@ProductID],Products[ProductID],Products[COGSPct]) | H13: =[@ARR]-[@AnnualCOGS]
A14: C011 | B14: Apex Analytics | C14: Mid-Market | D14: P005 | E14: =XLOOKUP([@ProductID],Products[ProductID],Products[AnnualPrice]) | F14: Active | G14: =[@ARR]*XLOOKUP([@ProductID],Products[ProductID],Products[COGSPct]) | H14: =[@ARR]-[@AnnualCOGS]
A15: C012 | B15: ClearPath | C15: Enterprise | D15: P003 | E15: =XLOOKUP([@ProductID],Products[ProductID],Products[AnnualPrice]) | F15: Active | G15: =[@ARR]*XLOOKUP([@ProductID],Products[ProductID],Products[COGSPct]) | H15: =[@ARR]-[@AnnualCOGS]

Sheet Projections
A1: 5-Year Revenue Projections
A2: Uses named ranges (EBITDAMargin, TaxRate, …), LET, and SEQUENCE (spill)
A4: Year | B4: =SEQUENCE(1,5,2025)
A5: Base ARR ($) | B5: =SUM(Customers[ARR]) | C5: =ROUND(B5*(1+INDEX(GrowthRates,1)),0) | D5: =ROUND(C5*(1+INDEX(GrowthRates,2)),0) | E5: =ROUND(D5*(1+INDEX(GrowthRates,3)),0) | F5: =ROUND(E5*(1+INDEX(GrowthRates,4)),0)
A6: EBITDA ($) | B6: =ROUND(B5*EBITDAMargin,0) | C6: =ROUND(C5*EBITDAMargin,0) | D6: =ROUND(D5*EBITDAMargin,0) | E6: =ROUND(E5*EBITDAMargin,0) | F6: =ROUND(F5*EBITDAMargin,0)
A7: D&A ($) | B7: =ROUND(B5*DandAPct,0) | C7: =ROUND(C5*DandAPct,0) | D7: =ROUND(D5*DandAPct,0) | E7: =ROUND(E5*DandAPct,0) | F7: =ROUND(F5*DandAPct,0)
A8: EBIT ($) | B8: =B6-B7 | C8: =C6-C7 | D8: =D6-D7 | E8: =E6-E7 | F8: =F6-F7
A9: Taxes ($) | B9: =MAX(B8*TaxRate,0) | C9: =MAX(C8*TaxRate,0) | D9: =MAX(D8*TaxRate,0) | E9: =MAX(E8*TaxRate,0) | F9: =MAX(F8*TaxRate,0)
A10: NOPAT ($) | B10: =B8-B9 | C10: =C8-C9 | D10: =D8-D9 | E10: =E8-E9 | F10: =F8-F9
A11: CapEx ($) | B11: =ROUND(B5*CapexPct,0) | C11: =ROUND(C5*CapexPct,0) | D11: =ROUND(D5*CapexPct,0) | E11: =ROUND(E5*CapexPct,0) | F11: =ROUND(F5*CapexPct,0)
A12: Free Cash Flow ($) | B12: =LET(nopat,B10,da,B7,capex,B11,nopat+da-capex) | C12: =LET(nopat,C10,da,C7,capex,C11,nopat+da-capex) | D12: =LET(nopat,D10,da,D7,capex,D11,nopat+da-capex) | E12: =LET(nopat,E10,da,E7,capex,E11,nopat+da-capex) | F12: =LET(nopat,F10,da,F7,capex,F11,nopat+da-capex)

Sheet DCF
A1: Discounted Cash Flow Model
A2: Named ranges: DiscountRate, TerminalGrowthRate | LET for terminal value
A4: WACC (DiscountRate) | B4: =DiscountRate
A5: Terminal Growth Rate | B5: =TerminalGrowthRate
A6: Tax Rate | B6: =TaxRate
B8: Yr 1 | C8: Yr 2 | D8: Yr 3 | E8: Yr 4 | F8: Yr 5
A9: Free Cash Flow ($) | B9: =Projections!B12 | C9: =Projections!C12 | D9: =Projections!D12 | E9: =Projections!E12 | F9: =Projections!F12
A10: Discount Factor | B10: =1/(1+DiscountRate)^1 | C10: =1/(1+DiscountRate)^2 | D10: =1/(1+DiscountRate)^3 | E10: =1/(1+DiscountRate)^4 | F10: =1/(1+DiscountRate)^5
A11: PV of FCF ($) | B11: =B9*B10 | C11: =C9*C10 | D11: =D9*D10 | E11: =E9*E10 | F11: =F9*F10
A13: Sum PV of FCFs ($) | B13: =SUM(B11:F11)
A14: NPV check ($) | B14: =NPV(DiscountRate,B9:F9)
A15: Terminal Value PV ($) | B15: =LET(last_fcf,F9,tv,last_fcf*(1+TerminalGrowthRate)/(DiscountRate-TerminalGrowthRate),pv_tv,tv/(1+DiscountRate)^5,pv_tv)
A17: Enterprise Value ($) | B17: =B13+B15

Sheet Summary
A1: Executive Summary — Dynamic Array Demo
A2: UNIQUE / FILTER / spill-range (#) — features invisible to regex parsers
A4: Key Metrics
A5: Total Current ARR ($) | B5: =SUM(Customers[ARR])
A6: Active Customers | B6: =COUNTIF(Customers[Status],"Active")
A7: Avg ARR per Customer ($) | B7: =IFERROR(B5/B6,0)
A8: Enterprise Value ($) | B8: =DCF!B17
A10: ARR by Segment (UNIQUE spill + SUMIF on A11#)
A11: Segment | B11: Total ARR ($) | C11: % of Total
A12: =UNIQUE(Customers[Segment]) | B12: =SUMIF(Customers[Segment],A12#,Customers[ARR]) | C12: =B12#/SUM(Customers[ARR])
A18: Active Customers (FILTER spill)
A19: Name | B19: Segment | C19: ARR ($)
A20: =FILTER(Customers[CustomerName],Customers[Status]="Active") | B20: =FILTER(Customers[Segment],Customers[Status]="Active") | C20: =FILTER(Customers[ARR],Customers[Status]="Active")
